brucityslots/__init__.py
brucityslots/app.py
brucityslots-0.1.2.dist-info/METADATA
brucityslots-0.1.2.dist-info/WHEEL
brucityslots-0.1.2.dist-info/entry_points.txt
brucityslots-0.1.2.dist-info/RECORD
