Metadata-Version: 2.1
Name: brucityslots
Version: 0.1.2
Summary: 
Author: Lukas Valatka
Author-email: lukas.valatka123@gmail.com
Requires-Python: >=3.8,<4.0
Classifier: Programming Language :: Python :: 3
Classifier: Programming Language :: Python :: 3.8
Classifier: Programming Language :: Python :: 3.9
Classifier: Programming Language :: Python :: 3.10
Classifier: Programming Language :: Python :: 3.11
Requires-Dist: pydantic (>=2.3,<3.0)
Requires-Dist: python-dateutil (>=2.8,<3.0)
Requires-Dist: requests (>=2.28.1,<3.0.0)
